LICENSE.txt
MANIFEST.in
README.md
setup.cfg
setup.py
uwsift/__init__.py
uwsift/__main__.py
uwsift/common.py
uwsift/queue.py
uwsift/satpy_compat.py
uwsift/version.py
uwsift.egg-info/PKG-INFO
uwsift.egg-info/SOURCES.txt
uwsift.egg-info/dependency_links.txt
uwsift.egg-info/entry_points.txt
uwsift.egg-info/not-zip-safe
uwsift.egg-info/requires.txt
uwsift.egg-info/top_level.txt
uwsift/control/__init__.py
uwsift/control/doc_ws_as_timeline_scene.py
uwsift/control/file_behaviors.py
uwsift/control/layer_tree.py
uwsift/control/rgb_behaviors.py
uwsift/data/shadedrelief.jpg
uwsift/data/colormaps/OAX/Cloud Amount Default.cmap
uwsift/data/colormaps/OAX/Cloud Top Height.cmap
uwsift/data/colormaps/OAX/Low Cloud Base.cmap
uwsift/data/colormaps/OAX/Rain Rate.cmap
uwsift/data/colormaps/OAX/prob_severe.cmap
uwsift/data/colormaps/OAX/GOES-R/GOESR-L2/ACTP.cmap
uwsift/data/colormaps/OAX/GOES-R/GOESR-L2/ADP.cmap
uwsift/data/colormaps/OAX/GOES-R/GOESR-L2/CSM.cmap
uwsift/data/colormaps/OAX/GOES-R/GOESR-L2/Dust.cmap
uwsift/data/colormaps/OAX/GOES-R/GOESR-L2/FSC.cmap
uwsift/data/colormaps/OAX/GOES-R/GOESR-L2/GOES-SST-35.cmap
uwsift/data/colormaps/OAX/GOES-R/GOESR-L2/RRQPE.cmap
uwsift/data/colormaps/OAX/GOES-R/GOESR-L2/RRQPE1.cmap
uwsift/data/colormaps/OAX/GOES-R/GOESR-L2/Smoke.cmap
uwsift/data/colormaps/OAX/GOES-R/GOESR-L2/VTRSB.cmap
uwsift/data/colormaps/OAX/GOES-R/GOESR-L2/color-cape-10.cmap
uwsift/data/colormaps/OAX/GOES-R/GOESR-L2/color-li-10.cmap
uwsift/data/colormaps/OAX/GOES-R/GOESR-L2/color-pw10-10.cmap
uwsift/data/colormaps/OAX/GOES-R/GOESR-L2/color-pw8-10.cmap
uwsift/data/colormaps/OAX/GOES-R/IR/CIRA (IR Default).cmap
uwsift/data/colormaps/OAX/GOES-R/IR/IR WV.cmap
uwsift/data/colormaps/OAX/GOES-R/IR/IR_Color_Clouds_Summer.cmap
uwsift/data/colormaps/OAX/GOES-R/IR/IR_Color_Clouds_Winter.cmap
uwsift/data/colormaps/OAX/GOES-R/IR/Rainbow_11_bit.cmap
uwsift/data/colormaps/OAX/GOES-R/IR/WV_Dry_Yellow.cmap
uwsift/data/colormaps/OAX/GOES-R/IR/dust_and_moisture_split_window.cmap
uwsift/data/colormaps/OAX/GOES-R/IR/enhanced-rainbow-11.cmap
uwsift/data/colormaps/OAX/GOES-R/IR/enhanced-rainbow_warmer_yellow.cmap
uwsift/data/colormaps/OAX/GOES-R/IR/fire_detection_3.9.cmap
