Metadata-Version: 2.1
Name: uwsift
Version: 1.2.0
Summary: Satellite Information Familiarization Tool
Home-page: https://github.com/ssec/sift
Author: R.K.Garcia, University of Wisconsin - Madison Space Science & Engineering Center
Author-email: rkgarcia@wisc.edu
License: UNKNOWN
Platform: UNKNOWN
Classifier: Development Status :: 5 - Production/Stable
Classifier: Intended Audience :: Science/Research
Classifier: License :: OSI Approved :: GNU General Public License v3 or later (GPLv3+)
Classifier: Operating System :: OS Independent
Classifier: Programming Language :: Python
Classifier: Programming Language :: Python :: 3
Classifier: Topic :: Scientific/Engineering
Requires-Python: >=3.6
Provides-Extra: docs
